adz/__init__.py
adz/api.py
adz/cfg.py
adz/cli.py
adz/echo.py
tests/adz/__init__.py
tests/adz/test_api.py
tests/adz/test_cfg.py
tests/adz/test_cli.py
tests/adz/test_echo.py
adz-0.6.0.dist-info/METADATA
adz-0.6.0.dist-info/WHEEL
adz-0.6.0.dist-info/entry_points.txt
adz-0.6.0.dist-info/top_level.txt
adz-0.6.0.dist-info/RECORD
