Metadata-Version: 2.1
Name: adz
Version: 0.6.0
Summary: Command line interface for HTTP requests defined in yaml configuration file
Home-page: https://github.com/ambrozic/adz
Author: ambrozic
Author-email: ambrozic@gmail.com
Maintainer: ambrozic
Maintainer-email: ambrozic@gmail.com
License: BSD
Project-URL: Code, https://github.com/ambrozic/adz
Project-URL: Documentation, https://github.com/ambrozic/adz
Keywords: cli http requests yaml
Platform: UNKNOWN
Classifier: Programming Language :: Python
Classifier: Environment :: Web Environment
Classifier: Operating System :: MacOS :: MacOS X
Classifier: Operating System :: POSIX
Classifier: License :: OSI Approved :: BSD License
Classifier: Programming Language :: Python :: 3
Classifier: Programming Language :: Python :: 3.6
Classifier: Programming Language :: Python :: 3.7
Classifier: Topic :: Internet
Classifier: Topic :: Software Development :: Libraries :: Python Modules
Classifier: Intended Audience :: Developers
Requires-Python: >=3.6
Requires-Dist: click (<8.0,==7.0)
Requires-Dist: pyaml (<20.0,>=19.4)
Requires-Dist: pygments (<3.0,>=2.4)
Requires-Dist: requests (<3.0.0,>=2.0.0)
Provides-Extra: tests
Requires-Dist: black (==19.10b0) ; extra == 'tests'
Requires-Dist: codecov (<3.0,>=2.0) ; extra == 'tests'
Requires-Dist: isort (<5.0,>4.0) ; extra == 'tests'
Requires-Dist: pipdeptree (<1.0,>=0.13) ; extra == 'tests'
Requires-Dist: pytest-asyncio (==0.10.0) ; extra == 'tests'
Requires-Dist: pytest-cov (<3.0,>=2.7) ; extra == 'tests'
Requires-Dist: pytest (<6.0,>=5.0) ; extra == 'tests'
Requires-Dist: uvicorn (<0.9.0,>=0.8.0) ; extra == 'tests'
